adaptivefoldts/__init__.py
adaptivefoldts/core.py
adaptivefoldts/heap.py
adaptivefoldts/validation.py
AdaptiveFoldTS-1.0.1.dist-info/LICENSE
AdaptiveFoldTS-1.0.1.dist-info/METADATA
AdaptiveFoldTS-1.0.1.dist-info/WHEEL
AdaptiveFoldTS-1.0.1.dist-info/top_level.txt
AdaptiveFoldTS-1.0.1.dist-info/RECORD
