Metadata-Version: 2.1
Name: AdaptiveFoldTS
Version: 1.0.1
Summary: Validação Cruzada Adaptativa para Séries Temporais com Priorização Inteligente de Folds
Home-page: https://github.com/allanfenelon/AdaptiveFoldTS
Author: Allan Pereira Fenelon
Author-email: allanpereira.fenelon@example.com
License: UNKNOWN
Platform: UNKNOWN
Classifier: Programming Language :: Python :: 3
Classifier: License :: OSI Approved :: MIT License
Classifier: Operating System :: OS Independent
Classifier: Topic :: Scientific/Engineering :: Artificial Intelligence
Classifier: Topic :: Software Development :: Libraries
Requires-Python: >=3.7
License-File: LICENSE
Requires-Dist: numpy
Requires-Dist: pandas
Requires-Dist: scikit-learn
